{
  "products": [
    {
      "id": 1,
      "name": "غذای خشک گربه پرتوئین بالا",
      "brand": "دکتر هاس",
      "price": 250000,
      "originalPrice": 300000,
      "image": "/images/image.png",
      "category": "cat-food",
      "brand_category": "doctor-haas",
      "stock": true,
      "rating": 4.5,
      "reviews": 48,
      "description": "غذای خشک با کیفیت بالا برای گربه‌ها"
    },
    {
      "id": 2,
      "name": "اسباب بازی گربه رنگی",
      "brand": "فنبی",
      "price": 85000,
      "originalPrice": 110000,
      "image": "/images/image.png",
      "category": "cat-treats",
      "brand_category": "fenbi",
      "stock": true,
      "rating": 4.8,
      "reviews": 32,
      "description": "اسباب بازی رنگی و جذاب برای سرگرمی گربه"
    },
    {
      "id": 3,
      "name": "تشویقی سگ معلق",
      "brand": "ونپی",
      "price": 120000,
      "originalPrice": 150000,
      "image": "/images/image.png",
      "category": "dog-treats",
      "brand_category": "vanpi",
      "stock": true,
      "rating": 4.6,
      "reviews": 25,
      "description": "تشویقی درجه اول برای سگ‌ها"
    },
    {
      "id": 4,
      "name": "برس پرزگیر حرفه‌ای",
      "brand": "وینستون",
      "price": 140000,
      "originalPrice": 170000,
      "image": "/images/image.png",
      "category": "hygiene",
      "brand_category": "winston",
      "stock": true,
      "rating": 4.9,
      "reviews": 61,
      "description": "برس حرفه‌ای برای پرزگیری"
    },
    {
      "id": 5,
      "name": "ظرف غذای طراح‌شده",
      "brand": "دکتر هاس",
      "price": 95000,
      "image": "/images/image.png",
      "category": "food-bowls",
      "brand_category": "doctor-haas",
      "stock": true,
      "rating": 4.3,
      "reviews": 19,
      "description": "ظرف غذای دستطراح شده"
    },
    {
      "id": 6,
      "name": "پرزگیر خودکار",
      "brand": "فنبی",
      "price": 280000,
      "image": "/images/image.png",
      "category": "hygiene",
      "brand_category": "fenbi",
      "stock": true,
      "rating": 4.7,
      "reviews": 42,
      "description": "پرزگیر خودکار حرفه‌ای"
    },
    {
      "id": 7,
      "name": "غذای مرطوب گربه",
      "brand": "ونپی",
      "price": 65000,
      "originalPrice": 85000,
      "image": "/images/image.png",
      "category": "cat-food",
      "brand_category": "vanpi",
      "stock": true,
      "rating": 4.4,
      "reviews": 28,
      "description": "غذای مرطوب با طعم‌های مختلف"
    },
    {
      "id": 8,
      "name": "تشویقی ماهی سگ",
      "brand": "وینستون",
      "price": 145000,
      "image": "/images/image.png",
      "category": "dog-treats",
      "brand_category": "winston",
      "stock": true,
      "rating": 4.8,
      "reviews": 55,
      "description": "تشویقی طبیعی با طعم ماهی"
    },
    {
      "id": 9,
      "name": "خانه‌ی گربه پارچه‌ای",
      "brand": "دکتر هاس",
      "price": 320000,
      "originalPrice": 400000,
      "image": "/images/image.png",
      "category": "accessories",
      "brand_category": "doctor-haas",
      "stock": false,
      "rating": 4.6,
      "reviews": 37,
      "description": "خانه‌ی پارچه‌ای برای استراحت"
    },
    {
      "id": 10,
      "name": "دستکش پرزگیری",
      "brand": "فنبی",
      "price": 55000,
      "image": "/images/image.png",
      "category": "hygiene",
      "brand_category": "fenbi",
      "stock": true,
      "rating": 4.5,
      "reviews": 21,
      "description": "دستکش درجه اول برای پرزگیری"
    },
    {
      "id": 11,
      "name": "غذای سگ درجه یک",
      "brand": "ونپی",
      "price": 420000,
      "originalPrice": 520000,
      "image": "/images/image.png",
      "category": "dog-food",
      "brand_category": "vanpi",
      "stock": true,
      "rating": 4.9,
      "reviews": 78,
      "description": "غذای درجه یک برای سگ‌ها"
    },
    {
      "id": 12,
      "name": "قلادوی گربه",
      "brand": "وینستون",
      "price": 35000,
      "image": "/images/image.png",
      "category": "accessories",
      "brand_category": "winston",
      "stock": true,
      "rating": 4.3,
      "reviews": 15,
      "description": "قلاده ایمن برای گربه‌ها"
    }
  ],
  "categories": [
    { "id": "cat-food", "label": "غذای گربه", "parent": "food-bowls" },
    { "id": "cat-treats", "label": "تشویقی گربه", "parent": "cat" },
    { "id": "dog-food", "label": "غذای سگ", "parent": "food" },
    { "id": "dog-treats", "label": "تشویقی سگ", "parent": "dog" },
    { "id": "food-bowls", "label": "ظرف غذای حیوانات", "parent": "accessories" },
    { "id": "hygiene", "label": "بهداشتی", "parent": "care" },
    { "id": "accessories", "label": "اکسسوری", "parent": "other" }
  ],
  "brands": [
    { "id": "doctor-haas", "label": "دکتر هاس" },
    { "id": "fenbi", "label": "فنبی" },
    { "id": "vanpi", "label": "ونپی" },
    { "id": "winston", "label": "وینستون" }
  ]
}
